Workbook

Sheet Income Statement (normal)
A1: Year | B1: Total Revenue | C1: Automotive Sales Revenue | D1: Automotive Regulatory Credits | E1: Automotive Leasing Revenue | F1: Energy Revenue | G1: Services Revenue | H1: Cost of Revenue | I1: Gross Profit | J1: R&D Expense | K1: SG&A Expense | L1: Restructuring Expense | M1: Total Operating Expenses | N1: Operating Income | O1: Interest Income | P1: Interest Expense | Q1: Other Income | R1: Income Before Taxes | S1: Tax Provision | T1: Net Income
A2: 2022 | B2: 81462 | C2: 67210 | D2: 1776 | E2: 2476 | F2: 3909 | G2: 6091 | H2: 60609 | I2: 20853 | J2: 3075 | K2: 3946 | L2: 176 | M2: 7197 | N2: 13656 | O2: 297 | P2: -191 | Q2: -43 | R2: 13719 | S2: 1132 | T2: 12587
A3: 2023 | B3: 96773 | C3: 78509 | D3: 1790 | E3: 2120 | F3: 6035 | G3: 8319 | H3: 79113 | I3: 17660 | J3: 3969 | K3: 4800 | L3: 0 | M3: 8769 | N3: 8891 | O3: 1066 | P3: -156 | Q3: 172 | R3: 9973 | S3: -5001 | T3: 14974
A4: 2024 | B4: 97690 | C4: 72480 | D4: 2763 | E4: 1827 | F4: 10086 | G4: 10534 | H4: 80240 | I4: 17450 | J4: 4540 | K4: 5150 | L4: 684 | M4: 10374 | N4: 7076 | O4: 1569 | P4: -350 | Q4: 695 | R4: 8990 | S4: 1837 | T4: 7153
A5: 2025E | B5: 107725 | C5: 80002 | F5: 14423 | G5: 13300 | H5: 87843.533 | I5: 19881.467 | J5: 4641.5869 | K5: 5400.9019 | L5: 0 | M5: 10042.489 | N5: 9838.9778 | O5: 1615.875 | P5: -377.0375 | Q5: 646.35 | R5: 11724.165 | S5: 2462.0747 | T5: 9262.0906
A6: 2026E | B6: 123353 | C6: 86103 | F6: 20192 | G6: 16758 | H6: 100093.86 | I6: 23259.145 | J6: 5234.0179 | K6: 6058.2147 | L6: 0 | M6: 11292.233 | N6: 11966.912 | O6: 1850.295 | P6: -431.7355 | Q6: 740.118 | R6: 14125.59 | S6: 2966.3738 | T6: 11159.216
A7: 2027E | B7: 146046 | C7: 94162 | F7: 28269 | G7: 21115 | H7: 117923.73 | I7: 28122.266 | J7: 6101.081 | K7: 7023.3002 | L7: 0 | M7: 13124.381 | N7: 14997.885 | O7: 2190.69 | P7: -511.161 | Q7: 876.276 | R7: 17553.69 | S7: 3686.2749 | T7: 13867.415
A8: 2028E | B8: 186125 | C8: 102943 | F8: 39577 | G8: 26605 | H8: 149540.72 | I8: 36584.282 | J8: 7653.2573 | K8: 8760.245 | L8: 0 | M8: 16413.502 | N8: 20170.78 | O8: 2791.875 | P8: -651.4375 | Q8: 1116.75 | R8: 23427.967 | S8: 4919.8731 | T8: 18508.094
A9: 2029E | B9: 234425 | C9: 112495 | F9: 55408 | G9: 33522 | H9: 187409.29 | I9: 47015.714 | J9: 9485.4821 | K9: 10793.695 | L9: 0 | M9: 20279.177 | N9: 26736.536 | O9: 3516.375 | P9: -820.4875 | Q9: 1406.55 | R9: 30838.974 | S9: 6476.1845 | T9: 24362.789
A10: 2030E | B10: 292679 | C10: 122870 | F10: 77571 | G10: 42238 | H10: 232809.29 | I10: 59869.711 | J10: 11650.557 | K10: 13176.436 | L10: 0 | M10: 24826.993 | N10: 35042.718 | O10: 4390.185 | P10: -1024.3765 | Q10: 1756.074 | R10: 40164.601 | S10: 8434.5662 | T10: 31730.035

Sheet Balance Sheet (normal)
A1: Year | B1: Cash | C1: Short Term Investments | D1: Accounts Receivable | E1: Inventory | F1: Prepaid Expenses | G1: Total Current Assets | H1: PPE Net | I1: Total Assets | J1: Accounts Payable | K1: Accrued Liabilities | L1: Deferred Revenue | M1: Current Debt | N1: Long Term Debt | O1: Total Liabilities | P1: Total Equity | Q1: Retained Earnings
A2: 2022
A3: 2023 | B3: 16398 | C3: 12696 | D3: 3508 | E3: 13626 | F3: 3388 | G3: 49616 | H3: 29725 | I3: 106618 | J3: 14431 | K3: 9080 | L3: 2864 | M3: 2373 | N3: 2857 | O3: 43009 | P3: 62634 | Q3: 27882
A4: 2024 | B4: 16139 | C4: 20424 | D4: 4418 | E4: 12017 | F4: 5362 | G4: 58360 | H4: 35836 | I4: 122070 | J4: 12474 | K4: 10723 | L4: 3168 | M4: 2456 | N4: 5757 | O4: 48390 | P4: 72913 | Q4: 35209
A5: 2025E | B5: 16077.451 | D5: 11805.479 | E5: 13663.918 | G5: =SUM(B5:F5) -> 41546.848 | H5: 38781 | I5: 123672.7 | J5: 14004.25 | K5: 11849.75 | L5: 3447.2 | M5: 2136.5328 | N5: 4985.2432 | O5: 43707.571 | P5: 79965.128 | Q5: 43544.882
A6: 2026E | B6: 18055.821 | D6: 13518.137 | E6: 15128.791 | G6: =SUM(B6:F6) -> 46702.749 | H6: 41940.02 | I6: 138890.93 | J6: 16035.89 | K6: 13568.83 | L6: 3947.296 | M6: 2375.2017 | N6: 5542.1372 | O6: 49763.226 | P6: 89127.703 | Q6: 53588.176
A7: 2027E | B7: 20974.164 | D7: 16005.041 | E7: 17333.146 | G7: =SUM(B7:F7) -> 54312.352 | H7: 46734.72 | I7: 161339.72 | J7: 18985.98 | K7: 16065.06 | L7: 4673.472 | M7: 2730.9489 | N7: 6372.2141 | O7: 58593.21 | P7: 102746.51 | Q7: 66068.849
A8: 2028E | B8: 26235.045 | D8: 20397.26 | E8: 21391.642 | G8: =SUM(B8:F8) -> 68023.947 | H8: 55837.5 | I8: 201808.04 | J8: 24196.25 | K8: 20473.75 | L8: 5956 | M8: 3380.728 | N8: 7888.3652 | O8: 74274.112 | P8: 127533.93 | Q8: 82726.134
A9: 2029E | B9: 32442.335 | D9: 25690.411 | E9: 26109.343 | G9: =SUM(B9:F9) -> 84242.089 | H9: 65639 | I9: 249556.42 | J9: 30475.25 | K9: 25786.75 | L9: 7501.6 | M9: 4137.0701 | N9: 9653.1636 | O9: 93064.6 | P9: 156491.82 | Q9: 104652.64
A10: 2030E | B10: 39780.881 | D10: 32074.411 | E10: 31609.744 | G10: =SUM(B10:F10) -> 103465.04 | H10: 76096.54 | I10: 306006.78 | J10: 38048.27 | K10: 32194.69 | L10: 9365.728 | M10: 5019.4881 | N10: 11712.139 | O10: 115608.38 | P10: 190398.4 | Q10: 133209.68

Sheet Cash Flow (normal)
A1: Year | B1: Net Income | C1: Depreciation | D1: Operating Cash Flow | E1: Investing Cash Flow | F1: Financing Cash Flow | G1: Net Cash Flow
A2: 2022 | B2: 12587 | C2: 3747 | D2: 14724 | E2: -11973 | F2: -3527 | G2: -1220
A3: 2023 | B3: 14974 | C3: 4667 | D3: 13256 | E3: -15584 | F3: 2589 | G3: 265
A4: 2024 | B4: 7153 | C4: 5368 | D4: 14923 | E4: -18787 | F4: 3853 | G4: -152
A5: 2025E | B5: 9262.0906 | C5: 4300.32 | D5: 6058.263 | E5: -7245.32 | F5: -1554.3286 | G5: -2741.3856
A6: 2026E | B6: 11159.216 | C6: 4653.72 | D6: 14667.045 | E6: -7812.74 | F6: 237.60214 | G6: 7091.9072
A7: 2027E | B7: 13867.415 | C7: 5032.8024 | D7: 17159.048 | E7: -9827.5024 | F7: 492.45333 | G7: 7823.9992
A8: 2028E | B8: 18508.094 | C8: 5608.1664 | D8: 20875.816 | E8: -14710.946 | F8: 1240.5255 | G8: 7405.3948
A9: 2029E | B9: 24362.789 | C9: 6700.5 | D9: 27331.437 | E9: -16502 | F9: 1303.0011 | G9: 12132.438
A10: 2030E | B10: 31730.035 | C10: 7876.68 | D10: 35295.334 | E10: -18334.22 | F10: 1354.8916 | G10: 18316.006

Sheet Financial Ratios (normal)
A1: Year | B1: Gross_Margin | C1: Operating_Margin | D1: Net_Margin | E1: R&D_Ratio | F1: SG&A_Ratio | G1: Total_OpEx_Ratio | H1: Asset_Turnover | I1: Inventory_Turnover | J1: Debt_to_Assets | K1: Debt_to_Equity | L1: ROE | M1: ROA
A2: 2022 | B2: 0.25598439 | C2: 0.16763644 | D2: 0.15451376 | E2: 0.037747661 | F2: 0.048439763 | G2: 0.088347941
A3: 2023 | B3: 0.18248892 | C3: 0.0918748 | D3: 0.15473324 | E3: 0.041013506 | F3: 0.049600612 | G3: 0.090614118 | H3: 0.907661 | I3: 5.8060326 | J3: ='Balance Sheet (normal)'!O3/'Balance Sheet (normal)'!I3 -> 0.40339342 | K3: ='Balance Sheet (normal)'!O3/'Balance Sheet (normal)'!P3 -> 0.68667178 | L3: 0.23907143 | M3: 0.14044533
A4: 2024 | B4: 0.17862627 | C4: 0.072433207 | D4: 0.073221415 | E4: 0.046473539 | F4: 0.052717781 | G4: 0.10619306 | H4: 0.80027853 | I4: 6.6772073 | J4: ='Balance Sheet (normal)'!O4/'Balance Sheet (normal)'!I4 -> 0.39641189 | K4: ='Balance Sheet (normal)'!O4/'Balance Sheet (normal)'!P4 -> 0.66366766 | L4: 0.098103219 | M4: 0.058597526
A5: 2025E | B5: 0.18455759 | C5: 0.09133421 | D5: 0.085979026 | E5: ='Income Statement (normal)'!J5/'Income Statement (normal)'!B5 -> 0.043087369 | F5: ='Income Statement (normal)'!K5/'Income Statement (normal)'!B5 -> 0.050136012 | G5: ='Income Statement (normal)'!M5/'Income Statement (normal)'!B5 -> 0.093223382 | H5: 0.87104916 | I5: ='Income Statement (normal)'!B5/'Balance Sheet (normal)'!E5 -> 7.8839026 | J5: ='Balance Sheet (normal)'!O5/'Balance Sheet (normal)'!I5 -> 0.35341326 | K5: ='Balance Sheet (normal)'!O5/'Balance Sheet (normal)'!P5 -> 0.5465829 | L5: 0.11582662 | M5: 0.074891958
A6: 2026E | B6: 0.18855759 | C6: 0.097013547 | D6: 0.090465702 | E6: ='Income Statement (normal)'!J6/'Income Statement (normal)'!B6 -> 0.042431217 | F6: ='Income Statement (normal)'!K6/'Income Statement (normal)'!B6 -> 0.049112828 | G6: ='Income Statement (normal)'!M6/'Income Statement (normal)'!B6 -> 0.091544045 | H6: 0.88812855 | I6: ='Income Statement (normal)'!B6/'Balance Sheet (normal)'!E6 -> 8.1535264 | J6: ='Balance Sheet (normal)'!O6/'Balance Sheet (normal)'!I6 -> 0.35828996 | K6: ='Balance Sheet (normal)'!O6/'Balance Sheet (normal)'!P6 -> 0.55833623 | L6: 0.12520479 | M6: 0.080345173
A7: 2027E | B7: 0.19255759 | C7: 0.10269288 | D7: 0.094952378 | E7: ='Income Statement (normal)'!J7/'Income Statement (normal)'!B7 -> 0.041775064 | F7: ='Income Statement (normal)'!K7/'Income Statement (normal)'!B7 -> 0.048089644 | G7: ='Income Statement (normal)'!M7/'Income Statement (normal)'!B7 -> 0.089864708 | H7: 0.90520795 | I7: ='Income Statement (normal)'!B7/'Balance Sheet (normal)'!E7 -> 8.4258217 | J7: ='Balance Sheet (normal)'!O7/'Balance Sheet (normal)'!I7 -> 0.36316667 | K7: ='Balance Sheet (normal)'!O7/'Balance Sheet (normal)'!P7 -> 0.57026957 | L7: 0.13496726 | M7: 0.085951647
A8: 2028E | B8: 0.19655759 | C8: 0.10837222 | D8: 0.099439054 | E8: ='Income Statement (normal)'!J8/'Income Statement (normal)'!B8 -> 0.041118911 | F8: ='Income Statement (normal)'!K8/'Income Statement (normal)'!B8 -> 0.047066461 | G8: ='Income Statement (normal)'!M8/'Income Statement (normal)'!B8 -> 0.088185371 | H8: 0.92228734 | I8: ='Income Statement (normal)'!B8/'Balance Sheet (normal)'!E8 -> 8.7008282 | J8: ='Balance Sheet (normal)'!O8/'Balance Sheet (normal)'!I8 -> 0.36804338 | K8: ='Balance Sheet (normal)'!O8/'Balance Sheet (normal)'!P8 -> 0.58238708 | L8: 0.1451229 | M8: 0.091711381
A9: 2029E | B9: 0.20055759 | C9: 0.11405156 | D9: 0.10392573 | E9: ='Income Statement (normal)'!J9/'Income Statement (normal)'!B9 -> 0.040462758 | F9: ='Income Statement (normal)'!K9/'Income Statement (normal)'!B9 -> 0.046043277 | G9: ='Income Statement (normal)'!M9/'Income Statement (normal)'!B9 -> 0.086506035 | H9: 0.93936674 | I9: ='Income Statement (normal)'!B9/'Balance Sheet (normal)'!E9 -> 8.9785866 | J9: ='Balance Sheet (normal)'!O9/'Balance Sheet (normal)'!I9 -> 0.37292008 | K9: ='Balance Sheet (normal)'!O9/'Balance Sheet (normal)'!P9 -> 0.59469307 | L9: 0.15568091 | M9: 0.097624374
A10: 2030E | B10: 0.20455759 | C10: 0.11973089 | D10: 0.10841241 | E10: ='Income Statement (normal)'!J10/'Income Statement (normal)'!B10 -> 0.039806605 | F10: ='Income Statement (normal)'!K10/'Income Statement (normal)'!B10 -> 0.045020093 | G10: ='Income Statement (normal)'!M10/'Income Statement (normal)'!B10 -> 0.084826698 | H10: 0.95644613 | I10: ='Income Statement (normal)'!B10/'Balance Sheet (normal)'!E10 -> 9.2591386 | J10: ='Balance Sheet (normal)'!O10/'Balance Sheet (normal)'!I10 -> 0.37779679 | K10: ='Balance Sheet (normal)'!O10/'Balance Sheet (normal)'!P10 -> 0.60719196 | L10: 0.16665074 | M10: 0.10369063

Sheet Growth Analysis (normal)
A1: Year | B1: Revenue_Growth | C1: NetIncome_Growth
A2: 2022 | B2: 0 | C2: 0
A3: 2023 | B3: 0.18795267 | C3: 0.1896401
A4: 2024 | B4: 0.0094757835 | C4: -0.52230533
A5: 2025E | B5: 0.1027229 | C5: 0.29485399
A6: 2026E | B6: 0.1450731 | C6: 0.20482689
A7: 2027E | B7: 0.18396796 | C7: 0.24268724
A8: 2028E | B8: 0.27442724 | C8: 0.33464629
A9: 2029E | B9: 0.25950302 | C9: 0.31633162
A10: 2030E | B10: 0.24849739 | C10: 0.30239745

Sheet Revenue Details (normal)
A1: Year | B1: Revenue_Millions | C1: Revenue_Billions | D1: YoY_Growth
A2: 2022 | B2: 81462 | C2: 81.462 | D2: 0
A3: 2023 | B3: 96773 | C3: 96.773 | D3: 18.795267
A4: 2024 | B4: 97690 | C4: 97.69 | D4: 0.94757835
A5: 2025E | B5: 107725 | C5: 107.725 | D5: 10.27229
A6: 2026E | B6: 123353 | C6: 123.353 | D6: 14.50731
A7: 2027E | B7: 146046 | C7: 146.046 | D7: 18.396796
A8: 2028E | B8: 186125 | C8: 186.125 | D8: 27.442724
A9: 2029E | B9: 234425 | C9: 234.425 | D9: 25.950302
A10: 2030E | B10: 292679 | C10: 292.679 | D10: 24.849739

Sheet Executive Summary (normal)
A1: 指标 | B1: 数值
A2: 2024年实际收入（百万美元） | B2: $97,690
A3: 2030年预测收入（百万美元） | B3: $292,679
A4: 6年复合增长率（CAGR） | B4: 20.1%
A5: 2024年净利润率 | B5: 7.3%
A6: 2030年预测净利润率 | B6: 10.8%
A7: 2024年ROE | B7: 9.8%
A8: 2030年预测ROE | B8: 16.7%
A9: 2024年总资产（百万美元） | B9: $122,070
A10: 2030年预测总资产（百万美元） | B10: $306,007
